pyDeepInsight/__init__.py
pyDeepInsight/__init__.pyi
pyDeepInsight/feature_selection.py
pyDeepInsight/feature_selection.pyi
pyDeepInsight/image_transformer.py
pyDeepInsight/image_transformer.pyi
pyDeepInsight/py.typed
pyDeepInsight/utils/__init__.py
pyDeepInsight/utils/__init__.pyi
pyDeepInsight/utils/_assignment.py
pyDeepInsight/utils/_assignment.pyi
pyDeepInsight/utils/_norm2.py
pyDeepInsight/utils/_norm2.pyi
pyDeepInsight/utils/filters.py
pyDeepInsight/utils/filters.pyi
pyDeepInsight/utils/sampler.py
pyDeepInsight/utils/sampler.pyi
pydeepinsight-0.2.3.dist-info/licenses/LICENSE
pydeepinsight-0.2.3.dist-info/METADATA
pydeepinsight-0.2.3.dist-info/WHEEL
pydeepinsight-0.2.3.dist-info/top_level.txt
pydeepinsight-0.2.3.dist-info/RECORD
