Metadata-Version: 2.4
Name: pyDeepInsight
Version: 0.2.3
Summary: A methodology to transform a non-image data to an image for convolution neural network architecture
Author-email: "Keith A. Boroevich" <kaboroevich@gmail.com>
License:  GNU GENERAL PUBLIC LICENSE
Project-URL: Homepage, https://github.com/alok-ai-lab/pyDeepInsight
Keywords: deep-learning,feature-visualization,non-image data,data transformation,CNN,machine-learning,representation learning,grad-cam,pytorch,scikit-learn,dimensionality reduction,t-SNE,PCA,image encoding
Requires-Python: >=3.8
License-File: LICENSE
Requires-Dist: numpy
Requires-Dist: scipy
Requires-Dist: scikit-learn>=0.22
Requires-Dist: matplotlib
Requires-Dist: torch
Provides-Extra: cam
Requires-Dist: grad-cam; extra == "cam"
Requires-Dist: torchcam; extra == "cam"
Provides-Extra: ags
Requires-Dist: asymmetric-greedy-search; extra == "ags"
Requires-Dist: numba; extra == "ags"
Dynamic: license-file
